CHANGELOG.md
MANIFEST.in
README.md
requirements.txt
setup.py
cherab/__init__.py
cherab/openadas/VERSION
cherab/openadas/__init__.py
cherab/openadas/install.py
cherab/openadas/openadas.py
cherab/openadas/parse/__init__.py
cherab/openadas/parse/adf11.py
cherab/openadas/parse/adf12.py
cherab/openadas/parse/adf15.py
cherab/openadas/parse/adf21.py
cherab/openadas/parse/adf22.py
cherab/openadas/parse/utility.py
cherab/openadas/rates/__init__.pxd
cherab/openadas/rates/__init__.py
cherab/openadas/rates/beam.c
cherab/openadas/rates/beam.pxd
cherab/openadas/rates/beam.pyx
cherab/openadas/rates/cx.c
cherab/openadas/rates/cx.pxd
cherab/openadas/rates/cx.pyx
cherab/openadas/rates/pec.c
cherab/openadas/rates/pec.pxd
cherab/openadas/rates/pec.pyx
cherab/openadas/rates/radiated_power.c
cherab/openadas/rates/radiated_power.pyx
cherab/openadas/repository/__init__.py
cherab/openadas/repository/create.py
cherab/openadas/repository/pec.py
cherab/openadas/repository/utility.py
cherab/openadas/repository/wavelength.py
cherab/openadas/repository/beam/__init__.py
cherab/openadas/repository/beam/cx.py
cherab/openadas/repository/beam/emission.py
cherab/openadas/repository/beam/population.py
cherab/openadas/repository/beam/stopping.py
cherab_openadas.egg-info/PKG-INFO
cherab_openadas.egg-info/SOURCES.txt
cherab_openadas.egg-info/dependency_links.txt
cherab_openadas.egg-info/namespace_packages.txt
cherab_openadas.egg-info/not-zip-safe
cherab_openadas.egg-info/requires.txt
cherab_openadas.egg-info/top_level.txt