Metadata-Version: 1.1
Name: cherab-openadas
Version: 1.1.0
Summary: Cherab spectroscopy framework: OpenADAS atomic data source package
Home-page: UNKNOWN
Author: UNKNOWN
Author-email: UNKNOWN
License: EUPL 1.1
Platform: UNKNOWN
Classifier: Development Status :: 5 - Production/Stable
Classifier: Intended Audience :: Science/Research
Classifier: Intended Audience :: Education
Classifier: Intended Audience :: Developers
Classifier: Natural Language :: English
Classifier: Operating System :: POSIX :: Linux
Classifier: Programming Language :: Cython
Classifier: Programming Language :: Python :: 3
Classifier: Topic :: Scientific/Engineering :: Physics
